configjs/__init__.py
configjs/config.json
configjs-0.1.0.dist-info/LICENSE
configjs-0.1.0.dist-info/WHEEL
configjs-0.1.0.dist-info/METADATA
configjs-0.1.0.dist-info/RECORD
