Metadata-Version: 2.1
Name: configjs
Version: 0.1.0
Summary: A Python package to read "config.json" in the working directory and access its content using the package name itself.
Home-page: https://github.com/doosik71/configjs
Author: Doosik Kim
Author-email: doosik71@gmail.com
License: MIT
License-File: LICENSE
